LICENSE
MANIFEST.in
README.rst
setup.py
django_dynamic_link.egg-info/PKG-INFO
django_dynamic_link.egg-info/SOURCES.txt
django_dynamic_link.egg-info/dependency_links.txt
django_dynamic_link.egg-info/not-zip-safe
django_dynamic_link.egg-info/top_level.txt
dynamicLink/__init__.py
dynamicLink/__init__.pyc
dynamicLink/admin.py
dynamicLink/admin.pyc
dynamicLink/api.py
dynamicLink/api.pyc
dynamicLink/models.py
dynamicLink/models.pyc
dynamicLink/presettings.py
dynamicLink/presettings.pyc
dynamicLink/tests.py
dynamicLink/tests.pyc
dynamicLink/urls.py
dynamicLink/urls.pyc
dynamicLink/version.py
dynamicLink/version.pyc
dynamicLink/views.py
dynamicLink/views.pyc
dynamicLink/locale/de/LC_MESSAGES/django.mo
dynamicLink/locale/de/LC_MESSAGES/django.po
dynamicLink/locale/en/LC_MESSAGES/django.mo
dynamicLink/locale/en/LC_MESSAGES/django.po
dynamicLink/templates/dynamicLink/not_avallible.html
dynamicLink/templates/dynamicLink/provide.html
example/__init__.py
example/__init__.pyc
example/manage.py
example/settings.py
example/settings.pyc
example/urls.py
example/urls.pyc
example/media/django-logo-negative.png.tar.gz
example/media/django-logo-negative.svg.zip
example/media/django-logo-positive.png.tar.gz
example/media/django-logo-positive.svg.zip
example/templates/base.html
example/templates/home.html