Metadata-Version: 1.0
Name: django-dynamic-link
Version: 0.5.4
Summary: A django file streaming application
Home-page: http://www.sources.e-blue.eu/de/pages/django/
Author: Andreas Fritz
Author-email: djangp-dynamic-link@bitzeit.eu
License: BSD
Download-URL: https://bitbucket.org/catapela/django-dynamic-link/downloads
Keywords: django file streaming dynamic links serve
Platform: UNKNOWN
Classifier: Development Status :: 4 - Beta
Classifier: Framework :: Django
Classifier: License :: OSI Approved :: BSD License
Classifier: Operating System :: OS Independent
Classifier: Programming Language :: Python
Classifier: Environment :: Console
Classifier: Natural Language :: English
Classifier: Natural Language :: German
Classifier: Intended Audience :: Developers
Classifier: Intended Audience :: Information Technology
Classifier: Topic :: Internet
Classifier: Topic :: Utilities
